LICENSE
README.md
setup.py
requests_go/__init__.py
requests_go/__version__.py
requests_go/adapters.py
requests_go/api.py
requests_go/auth.py
requests_go/pool.py
requests_go/pool_provider.py
requests_go/request.py
requests_go/response.py
requests_go/sessions.py
requests_go.egg-info/PKG-INFO
requests_go.egg-info/SOURCES.txt
requests_go.egg-info/dependency_links.txt
requests_go.egg-info/requires.txt
requests_go.egg-info/top_level.txt
requests_go/tls_client/__init__.py
requests_go/tls_client/client.py
requests_go/tls_client/exceptions.py
requests_go/tls_client/request.py
requests_go/tls_client/response.py
requests_go/tls_client/structures.py
requests_go/tls_client/dependencies/__init__.py
requests_go/tls_client/dependencies/requests-go-amd64.so
requests_go/tls_client/dependencies/requests-go-arm64.dylib
requests_go/tls_client/dependencies/requests-go-arm64.so
requests_go/tls_client/dependencies/requests-go-win64.dll
requests_go/tls_client/dependencies/requests-go-x86.dylib
requests_go/tls_client/dependencies/requests-go-x86.so
requests_go/tls_config/__init__.py
requests_go/tls_config/algorithms.py
requests_go/tls_config/ciphers.py
requests_go/tls_config/config.py
requests_go/tls_config/convert_config.py
requests_go/tls_config/extensions.py