Metadata-Version: 2.1
Name: requests_go
Version: 1.0.7
Summary: Advanced Python HTTP/HTTP2 Client. Support tls/http2/ja3 Fingerprint Custom.
Home-page: https://github.com/wangluozhe/requests-go
Author: Lee Gene
Author-email: leegene0816@gmail.com
License: MIT
Classifier: Environment :: Web Environment
Classifier: Intended Audience :: Developers
Classifier: Natural Language :: English
Classifier: Operating System :: Unix
Classifier: Operating System :: MacOS :: MacOS X
Classifier: Operating System :: Microsoft :: Windows
Classifier: Programming Language :: Python
Classifier: Programming Language :: Python :: 3
Classifier: Topic :: Internet :: WWW/HTTP
Classifier: Topic :: Software Development :: Libraries
Requires-Python: >=3.7
License-File: LICENSE
Requires-Dist: requests>=2.28.1
Requires-Dist: six>=1.16.0
Requires-Dist: PySocks>=1.7.1
